dabo/dReportWriter.py
dabo/__init__.py
dabo/dPref.py
dabo/dUserSettingProvider.py
dabo/dBug.py
dabo/dLocalize.py
dabo/dColors.py
dabo/dApp.py
dabo/dConstants.py
dabo/dObject.py
dabo/dException.py
dabo/settings.py
dabo/dEvents.py
dabo/LICENSE.TXT
dabo/dSecurityManager.py
dabo/version.py
dabo/biz/__init__.py
dabo/biz/dAutoBizobj.py
dabo/biz/RemoteBizobj.py
dabo/biz/dBizobj.py
dabo/db/dbWeb.py
dabo/db/__init__.py
dabo/db/dbTemplate.py
dabo/db/dConnection.py
dabo/db/dbMySQL.py
dabo/db/dbPostgreSQL.py
dabo/db/dbSQLite.py
dabo/db/dTable.py
dabo/db/dConnectInfo.py
dabo/db/dbFirebird.py
dabo/db/dbMsSQL.py
dabo/db/dDataSet.py
dabo/db/dbOracle.py
dabo/db/dBackend.py
dabo/db/dCursorMixin.py
dabo/db/dNoEscQuoteStr.py
dabo/lib/logger.py
dabo/lib/__init__.py
dabo/lib/xmltodict.py
dabo/lib/caselessDict.py
dabo/lib/SimpleCrypt.py
dabo/lib/dejavuJSON.py
dabo/lib/manifest.py
dabo/lib/DesignerClassConverter.py
dabo/lib/StopWatch.py
dabo/lib/profilehooks.py
dabo/lib/eventMixin.py
dabo/lib/RemoteConnector.py
dabo/lib/EasyDialogBuilder.py
dabo/lib/reportUtils.py
dabo/lib/untabify.py
dabo/lib/DesignerUtils.py
dabo/lib/connParser.py
dabo/lib/dates.py
dabo/lib/specParser.py
dabo/lib/utils.py
dabo/lib/reportWriter.py
dabo/lib/propertyHelperMixin.py
dabo/lib/reporting_stefano/objects.py
dabo/lib/reporting_stefano/__init__.py
dabo/lib/reporting_stefano/report.py
dabo/lib/reporting_stefano/run.py
dabo/lib/reporting_stefano/util.py
dabo/lib/reporting_stefano/samplespec.rfxml
dabo/lib/reporting_stefano/serialization/__init__.py
dabo/lib/reporting_stefano/serialization/serialization.py
dabo/lib/reporting_stefano/serialization/xmlserializer.py
dabo/lib/reporting_stefano/serialization/children.py
dabo/lib/reporting_stefano/serialization/attributes.py
dabo/lib/datanav/__init__.py
dabo/lib/datanav/PageFrame.py
dabo/lib/datanav/Page.py
dabo/lib/datanav/Grid.py
dabo/lib/datanav/Bizobj.py
dabo/lib/datanav/Form.py
Dabo-0.9.16.dist-info/WHEEL
Dabo-0.9.16.dist-info/DESCRIPTION.rst
Dabo-0.9.16.dist-info/top_level.txt
Dabo-0.9.16.dist-info/metadata.json
Dabo-0.9.16.dist-info/METADATA
Dabo-0.9.16.dist-info/RECORD
