Metadata-Version: 2.0
Name: Dabo
Version: 0.9.16
Summary: Dabo 3-tier Application Framework
Home-page: http://dabodev.com/
Author: Ed Leafe and Paul McNett
Author-email: dev@dabodev.com
License: MIT
Download-URL: https://github.com/dabodev/dabo/archive/v0.9.16.zip
Platform: UNKNOWN
